saltext/influxdb/__init__.py
saltext/influxdb/version.py
saltext/influxdb/modules/__init__.py
saltext/influxdb/modules/influxdb08mod.py
saltext/influxdb/modules/influxdbmod.py
saltext/influxdb/returners/__init__.py
saltext/influxdb/returners/influxdb_return.py
saltext/influxdb/states/__init__.py
saltext/influxdb/states/influxdb08_database.py
saltext/influxdb/states/influxdb08_user.py
saltext/influxdb/states/influxdb_continuous_query.py
saltext/influxdb/states/influxdb_database.py
saltext/influxdb/states/influxdb_retention_policy.py
saltext/influxdb/states/influxdb_user.py
saltext.influxdb-1.0.0.dist-info/LICENSE
saltext.influxdb-1.0.0.dist-info/METADATA
saltext.influxdb-1.0.0.dist-info/NOTICE
saltext.influxdb-1.0.0.dist-info/WHEEL
saltext.influxdb-1.0.0.dist-info/entry_points.txt
saltext.influxdb-1.0.0.dist-info/top_level.txt
saltext.influxdb-1.0.0.dist-info/RECORD
